AUTHORS
CONTRIBUTING.rst
Gruntfile.js
INSTALL
LICENSE
LICENSE.python
MANIFEST.in
README.rst
package.json
pyproject.toml
setup.cfg
setup.py
extras/Makefile
extras/README.TXT
extras/django_bash_completion
js_tests/tests.html
js_tests/admin/DateTimeShortcuts.test.js
js_tests/admin/SelectBox.test.js
js_tests/admin/SelectFilter2.test.js
js_tests/admin/URLify.test.js
js_tests/admin/actions.test.js
js_tests/admin/core.test.js
js_tests/admin/inlines.test.js
js_tests/admin/jsi18n-mocks.test.js
js_tests/admin/navigation.test.js
js_tests/gis/mapwidget.test.js
paradoxdjango/__init__.py
paradoxdjango/__main__.py
paradoxdjango/shortcuts.py
paradoxdjango.egg-info/PKG-INFO
paradoxdjango.egg-info/SOURCES.txt
paradoxdjango.egg-info/dependency_links.txt
paradoxdjango.egg-info/entry_points.txt
paradoxdjango.egg-info/not-zip-safe
paradoxdjango.egg-info/requires.txt
paradoxdjango.egg-info/top_level.txt
paradoxdjango/apps/__init__.py
paradoxdjango/apps/config.py
paradoxdjango/apps/registry.py
paradoxdjango/conf/__init__.py
paradoxdjango/conf/global_settings.py
paradoxdjango/conf/app_template/__init__.py
paradoxdjango/conf/locale/__init__.py
paradoxdjango/conf/locale/ar/__init__.py
paradoxdjango/conf/locale/ar/formats.py
paradoxdjango/conf/locale/ar_DZ/__init__.py
paradoxdjango/conf/locale/ar_DZ/formats.py
paradoxdjango/conf/locale/az/__init__.py
paradoxdjango/conf/locale/az/formats.py
paradoxdjango/conf/locale/bg/__init__.py
paradoxdjango/conf/locale/bg/formats.py
paradoxdjango/conf/locale/bn/__init__.py
paradoxdjango/conf/locale/bn/formats.py
paradoxdjango/conf/locale/bs/__init__.py
paradoxdjango/conf/locale/bs/formats.py
paradoxdjango/conf/locale/ca/__init__.py
paradoxdjango/conf/locale/ca/formats.py
paradoxdjango/conf/locale/cs/__init__.py
paradoxdjango/conf/locale/cs/formats.py
paradoxdjango/conf/locale/cy/__init__.py
paradoxdjango/conf/locale/cy/formats.py
paradoxdjango/conf/locale/da/__init__.py
paradoxdjango/conf/locale/da/formats.py
paradoxdjango/conf/locale/de/__init__.py
paradoxdjango/conf/locale/de/formats.py
paradoxdjango/conf/locale/de_CH/__init__.py
paradoxdjango/conf/locale/de_CH/formats.py
paradoxdjango/conf/locale/el/__init__.py
paradoxdjango/conf/locale/el/formats.py
paradoxdjango/conf/locale/en/__init__.py
