Metadata-Version: 2.1
Name: paradoxdjango
Version: 0.0.4
Summary: A high-level Python web framework that encourages rapid development and clean, pragmatic design.
Home-page: https://www.djangoproject.com/
Author: Django Software Foundation
Author-email: foundation@djangoproject.com
License: BSD-3-Clause
Project-URL: Documentation, https://docs.djangoproject.com/
Project-URL: Release notes, https://docs.djangoproject.com/en/stable/releases/
Project-URL: Funding, https://www.djangoproject.com/fundraising/
Project-URL: Source, https://github.com/django/django
Project-URL: Tracker, https://code.djangoproject.com/
Platform: UNKNOWN
Classifier: Development Status :: 5 - Production/Stable
Classifier: Environment :: Web Environment
Classifier: Framework :: Django
Classifier: Intended Audience :: Developers
Classifier: License :: OSI Approved :: BSD License
Classifier: Operating System :: OS Independent
Classifier: Programming Language :: Python
Classifier: Programming Language :: Python :: 3
Classifier: Programming Language :: Python :: 3 :: Only
Classifier: Programming Language :: Python :: 3.8
Classifier: Programming Language :: Python :: 3.9
Classifier: Programming Language :: Python :: 3.10
Classifier: Topic :: Internet :: WWW/HTTP
Classifier: Topic :: Internet :: WWW/HTTP :: Dynamic Content
Classifier: Topic :: Internet :: WWW/HTTP :: WSGI
Classifier: Topic :: Software Development :: Libraries :: Application Frameworks
Classifier: Topic :: Software Development :: Libraries :: Python Modules
Requires-Python: >=3.8
Provides-Extra: argon2
Provides-Extra: bcrypt
License-File: LICENSE
License-File: LICENSE.python
License-File: AUTHORS
